chroma/Chroma.py
chroma/Chromosome.py
chroma/Chromosomes.py
chroma/Config.py
chroma/Cube.py
chroma/Cursor.py
chroma/Error.py
chroma/MainGui.py
chroma/Manager.py
chroma/Settings.py
chroma/Utils.py
chroma/ZoomWindow.py
chroma/__init__.py
chroma/__main__.py
chroma/config.json
chroma/main.py
chroma/icons/address-book-new.svg
chroma/icons/appointment-new.svg
chroma/icons/archive-insert-directory.svg
chroma/icons/archive-insert.svg
chroma/icons/bookmark-new.svg
chroma/icons/contact-new.svg
chroma/icons/dialog-apply.svg
chroma/icons/document-export.svg
chroma/icons/document-import.svg
chroma/icons/document-new.svg
chroma/icons/document-open-recent.svg
chroma/icons/document-open.svg
chroma/icons/document-page-setup.svg
chroma/icons/document-print-preview.svg
chroma/icons/document-print.svg
chroma/icons/document-properties.svg
chroma/icons/document-revert.svg
chroma/icons/document-save-as.svg
chroma/icons/document-save.svg
chroma/icons/edit-clear.svg
chroma/icons/edit-copy.svg
chroma/icons/edit-cut.svg
chroma/icons/edit-delete-mail.svg
chroma/icons/edit-delete.svg
chroma/icons/edit-paste.svg
chroma/icons/edit-redo.svg
chroma/icons/edit-select-all.svg
chroma/icons/edit-undo.svg
chroma/icons/extract-archive.svg
chroma/icons/folder-copy.svg
chroma/icons/folder-move.svg
chroma/icons/folder-new.svg
chroma/icons/go-bottom.svg
chroma/icons/go-down.svg
chroma/icons/go-first.svg
chroma/icons/go-home.svg
chroma/icons/go-jump.svg
chroma/icons/go-last.svg
chroma/icons/go-next.svg
chroma/icons/go-previous.svg
chroma/icons/go-top.svg
chroma/icons/go-up.svg
chroma/icons/gtk-edit.svg
chroma/icons/gtk-info.svg
chroma/icons/help-about.svg
chroma/icons/help-contents.svg
chroma/icons/help-hint.svg
chroma/icons/karyotype.svg
chroma/icons/legend.svg
chroma/icons/list-add.svg
chroma/icons/list-remove.svg
chroma/icons/media-eject.svg
chroma/icons/media-import-audio-cd.svg
chroma/icons/media-playback-pause.svg
chroma/icons/media-playback-start.svg
chroma/icons/media-playback-stop.svg
chromawizard-1.2.2.dist-info/LICENSE.txt
chromawizard-1.2.2.dist-info/METADATA
chromawizard-1.2.2.dist-info/WHEEL
chromawizard-1.2.2.dist-info/entry_points.txt
chromawizard-1.2.2.dist-info/top_level.txt
chromawizard-1.2.2.dist-info/RECORD
