Metadata-Version: 2.1
Name: chromawizard
Version: 1.2.2
Summary: Chromosome painting software
Home-page: https://gitlab.com/nauer/chromawizard
Author: Norbert Auer
Author-email: norbert.auer@boku.ac.at
License: GPL 3.0
Keywords: chromosome-painting FISH M-FISH CHO-K1
Platform: UNKNOWN
Classifier: Development Status :: 5 - Production/Stable
Classifier: Intended Audience :: Science/Research
Classifier: Topic :: Scientific/Engineering :: Visualization
Classifier: License :: OSI Approved :: GNU General Public License v3 or later (GPLv3+)
Classifier: Programming Language :: Python :: 3.5
Classifier: Programming Language :: Python :: 3.6
Requires-Dist: pillow (>=3.0.0)
Requires-Dist: numpy (>=1.10.2)
Requires-Dist: opencv-python (>=3.0.0)
Requires-Dist: PyQt5 (>=5.7)
